typeconvs/VERSION
typeconvs/__init__.py
typeconvs-0.2.1.dist-info/LICENSE.txt
typeconvs-0.2.1.dist-info/METADATA
typeconvs-0.2.1.dist-info/WHEEL
typeconvs-0.2.1.dist-info/top_level.txt
typeconvs-0.2.1.dist-info/RECORD
