Metadata-Version: 2.1
Name: typeconvs
Version: 0.2.1
Summary: Converters from str to another type.
Home-page: https://andreas19.github.io/typeconvs/
Author: Andreas Suhre
Author-email: andreas19@posteo.eu
License: BSD-3-Clause
Project-URL: Source code, https://github.com/andreas19/typeconvs/
Keywords: type converters
Platform: UNKNOWN
Classifier: Development Status :: 4 - Beta
Classifier: License :: OSI Approved :: BSD License
Classifier: Programming Language :: Python :: 3 :: Only
Classifier: Programming Language :: Python :: 3.8
Classifier: Intended Audience :: Developers
Classifier: Topic :: Software Development :: Libraries
Classifier: Operating System :: OS Independent
Requires-Python: >=3.8
License-File: LICENSE.txt
